Workbook

Sheet Read Me
A1: BCFA Manual Test Workbook
A2: Application | B2: Birla Carbon Finance Automation (x_695068_bcfa) on pwcmanagementservicesdemo01 (Yokohama)
A3: Version | B3: Phase 41, 2026-10-08
A4: Purpose | B4: Manual testing of the AP and Cash Application journeys end to end, from document intake to SAP posting / clearing and closure, plus extraction, tax, tolerances, deductions, AI, Playbooks, workspace, security and audit.
A5: How to use | B5: 1. Prepare data (sheet Test Data). 2. Run the E2E sheets first, then the Test Cases. 3. For every case record Actual Result, Status (Not Run / Pass / Fail / Blocked / N/A), Tester and Date. 4. Log failures in Defects and put the Defect ID on the case. 5. Summary counts the results.
A6: Placeholders | B6: <suffix> = the demo pack code (e.g. D2); <run> = the code printed by phase40_e2e_bg.js (e.g. 63D87).
A7: Personas | B7: Switch with Impersonate User from an admin account. Approvals must be decided by a different user from the requester and the processor (segregation of duties).
A8: Limits | B8: Test documents are SYNTHETIC except the client sample pack (P41-CS cases; kept out of source control); SAP is MOCK SAP; thresholds and tax rates are POC ASSUMPTION / POC REFERENCE DATA. Known platform limitation: Chinese VAT e-invoices and scanned Korean / Thai documents are not read (manual review).
A9: Shared instance | B9: Restore every property or integration profile you change for a negative test.

Sheet Summary
A1: Area | B1: Total | C1: Pass | D1: Fail | E1: Blocked | F1: Not Run | G1: N/A
A2: AP · Intake | B2: =COUNTIF('Test Cases'!B2:B95,A2) | C2: =COUNTIFS('Test Cases'!B2:B95,A2,'Test Cases'!L2:L95,"Pass") | D2: =COUNTIFS('Test Cases'!B2:B95,A2,'Test Cases'!L2:L95,"Fail") | E2: =COUNTIFS('Test Cases'!B2:B95,A2,'Test Cases'!L2:L95,"Blocked") | F2: =COUNTIFS('Test Cases'!B2:B95,A2,'Test Cases'!L2:L95,"Not Run") | G2: =COUNTIFS('Test Cases'!B2:B95,A2,'Test Cases'!L2:L95,"N/A")
A3: AP · Extraction | B3: =COUNTIF('Test Cases'!B2:B95,A3) | C3: =COUNTIFS('Test Cases'!B2:B95,A3,'Test Cases'!L2:L95,"Pass") | D3: =COUNTIFS('Test Cases'!B2:B95,A3,'Test Cases'!L2:L95,"Fail") | E3: =COUNTIFS('Test Cases'!B2:B95,A3,'Test Cases'!L2:L95,"Blocked") | F3: =COUNTIFS('Test Cases'!B2:B95,A3,'Test Cases'!L2:L95,"Not Run") | G3: =COUNTIFS('Test Cases'!B2:B95,A3,'Test Cases'!L2:L95,"N/A")
A4: AP · Validation | B4: =COUNTIF('Test Cases'!B2:B95,A4) | C4: =COUNTIFS('Test Cases'!B2:B95,A4,'Test Cases'!L2:L95,"Pass") | D4: =COUNTIFS('Test Cases'!B2:B95,A4,'Test Cases'!L2:L95,"Fail") | E4: =COUNTIFS('Test Cases'!B2:B95,A4,'Test Cases'!L2:L95,"Blocked") | F4: =COUNTIFS('Test Cases'!B2:B95,A4,'Test Cases'!L2:L95,"Not Run") | G4: =COUNTIFS('Test Cases'!B2:B95,A4,'Test Cases'!L2:L95,"N/A")
A5: AP · Tax | B5: =COUNTIF('Test Cases'!B2:B95,A5) | C5: =COUNTIFS('Test Cases'!B2:B95,A5,'Test Cases'!L2:L95,"Pass") | D5: =COUNTIFS('Test Cases'!B2:B95,A5,'Test Cases'!L2:L95,"Fail") | E5: =COUNTIFS('Test Cases'!B2:B95,A5,'Test Cases'!L2:L95,"Blocked") | F5: =COUNTIFS('Test Cases'!B2:B95,A5,'Test Cases'!L2:L95,"Not Run") | G5: =COUNTIFS('Test Cases'!B2:B95,A5,'Test Cases'!L2:L95,"N/A")
A6: AP · Tolerance | B6: =COUNTIF('Test Cases'!B2:B95,A6) | C6: =COUNTIFS('Test Cases'!B2:B95,A6,'Test Cases'!L2:L95,"Pass") | D6: =COUNTIFS('Test Cases'!B2:B95,A6,'Test Cases'!L2:L95,"Fail") | E6: =COUNTIFS('Test Cases'!B2:B95,A6,'Test Cases'!L2:L95,"Blocked") | F6: =COUNTIFS('Test Cases'!B2:B95,A6,'Test Cases'!L2:L95,"Not Run") | G6: =COUNTIFS('Test Cases'!B2:B95,A6,'Test Cases'!L2:L95,"N/A")
A7: AP · Match | B7: =COUNTIF('Test Cases'!B2:B95,A7) | C7: =COUNTIFS('Test Cases'!B2:B95,A7,'Test Cases'!L2:L95,"Pass") | D7: =COUNTIFS('Test Cases'!B2:B95,A7,'Test Cases'!L2:L95,"Fail") | E7: =COUNTIFS('Test Cases'!B2:B95,A7,'Test Cases'!L2:L95,"Blocked") | F7: =COUNTIFS('Test Cases'!B2:B95,A7,'Test Cases'!L2:L95,"Not Run") | G7: =COUNTIFS('Test Cases'!B2:B95,A7,'Test Cases'!L2:L95,"N/A")
A8: AP · Exceptions | B8: =COUNTIF('Test Cases'!B2:B95,A8) | C8: =COUNTIFS('Test Cases'!B2:B95,A8,'Test Cases'!L2:L95,"Pass") | D8: =COUNTIFS('Test Cases'!B2:B95,A8,'Test Cases'!L2:L95,"Fail") | E8: =COUNTIFS('Test Cases'!B2:B95,A8,'Test Cases'!L2:L95,"Blocked") | F8: =COUNTIFS('Test Cases'!B2:B95,A8,'Test Cases'!L2:L95,"Not Run") | G8: =COUNTIFS('Test Cases'!B2:B95,A8,'Test Cases'!L2:L95,"N/A")
A9: AP · Approval | B9: =COUNTIF('Test Cases'!B2:B95,A9) | C9: =COUNTIFS('Test Cases'!B2:B95,A9,'Test Cases'!L2:L95,"Pass") | D9: =COUNTIFS('Test Cases'!B2:B95,A9,'Test Cases'!L2:L95,"Fail") | E9: =COUNTIFS('Test Cases'!B2:B95,A9,'Test Cases'!L2:L95,"Blocked") | F9: =COUNTIFS('Test Cases'!B2:B95,A9,'Test Cases'!L2:L95,"Not Run") | G9: =COUNTIFS('Test Cases'!B2:B95,A9,'Test Cases'!L2:L95,"N/A")
A10: AP · SAP posting | B10: =COUNTIF('Test Cases'!B2:B95,A10) | C10: =COUNTIFS('Test Cases'!B2:B95,A10,'Test Cases'!L2:L95,"Pass") | D10: =COUNTIFS('Test Cases'!B2:B95,A10,'Test Cases'!L2:L95,"Fail") | E10: =COUNTIFS('Test Cases'!B2:B95,A10,'Test Cases'!L2:L95,"Blocked") | F10: =COUNTIFS('Test Cases'!B2:B95,A10,'Test Cases'!L2:L95,"Not Run") | G10: =COUNTIFS('Test Cases'!B2:B95,A10,'Test Cases'!L2:L95,"N/A")
A11: AP · Closure | B11: =COUNTIF('Test Cases'!B2:B95,A11) | C11: =COUNTIFS('Test Cases'!B2:B95,A11,'Test Cases'!L2:L95,"Pass") | D11: =COUNTIFS('Test Cases'!B2:B95,A11,'Test Cases'!L2:L95,"Fail") | E11: =COUNTIFS('Test Cases'!B2:B95,A11,'Test Cases'!L2:L95,"Blocked") | F11: =COUNTIFS('Test Cases'!B2:B95,A11,'Test Cases'!L2:L95,"Not Run") | G11: =COUNTIFS('Test Cases'!B2:B95,A11,'Test Cases'!L2:L95,"N/A")
A12: AP · Playbook | B12: =COUNTIF('Test Cases'!B2:B95,A12) | C12: =COUNTIFS('Test Cases'!B2:B95,A12,'Test Cases'!L2:L95,"Pass") | D12: =COUNTIFS('Test Cases'!B2:B95,A12,'Test Cases'!L2:L95,"Fail") | E12: =COUNTIFS('Test Cases'!B2:B95,A12,'Test Cases'!L2:L95,"Blocked") | F12: =COUNTIFS('Test Cases'!B2:B95,A12,'Test Cases'!L2:L95,"Not Run") | G12: =COUNTIFS('Test Cases'!B2:B95,A12,'Test Cases'!L2:L95,"N/A")
A13: AR · Bank line | B13: =COUNTIF('Test Cases'!B2:B95,A13) | C13: =COUNTIFS('Test Cases'!B2:B95,A13,'Test Cases'!L2:L95,"Pass") | D13: =COUNTIFS('Test Cases'!B2:B95,A13,'Test Cases'!L2:L95,"Fail") | E13: =COUNTIFS('Test Cases'!B2:B95,A13,'Test Cases'!L2:L95,"Blocked") | F13: =COUNTIFS('Test Cases'!B2:B95,A13,'Test Cases'!L2:L95,"Not Run") | G13: =COUNTIFS('Test Cases'!B2:B95,A13,'Test Cases'!L2:L95,"N/A")
A14: AR · Advice extraction | B14: =COUNTIF('Test Cases'!B2:B95,A14) | C14: =COUNTIFS('Test Cases'!B2:B95,A14,'Test Cases'!L2:L95,"Pass") | D14: =COUNTIFS('Test Cases'!B2:B95,A14,'Test Cases'!L2:L95,"Fail") | E14: =COUNTIFS('Test Cases'!B2:B95,A14,'Test Cases'!L2:L95,"Blocked") | F14: =COUNTIFS('Test Cases'!B2:B95,A14,'Test Cases'!L2:L95,"Not Run") | G14: =COUNTIFS('Test Cases'!B2:B95,A14,'Test Cases'!L2:L95,"N/A")
A15: AR · Customer | B15: =COUNTIF('Test Cases'!B2:B95,A15) | C15: =COUNTIFS('Test Cases'!B2:B95,A15,'Test Cases'!L2:L95,"Pass") | D15: =COUNTIFS('Test Cases'!B2:B95,A15,'Test Cases'!L2:L95,"Fail") | E15: =COUNTIFS('Test Cases'!B2:B95,A15,'Test Cases'!L2:L95,"Blocked") | F15: =COUNTIFS('Test Cases'!B2:B95,A15,'Test Cases'!L2:L95,"Not Run") | G15: =COUNTIFS('Test Cases'!B2:B95,A15,'Test Cases'!L2:L95,"N/A")
A16: AR · Open items | B16: =COUNTIF('Test Cases'!B2:B95,A16) | C16: =COUNTIFS('Test Cases'!B2:B95,A16,'Test Cases'!L2:L95,"Pass") | D16: =COUNTIFS('Test Cases'!B2:B95,A16,'Test Cases'!L2:L95,"Fail") | E16: =COUNTIFS('Test Cases'!B2:B95,A16,'Test Cases'!L2:L95,"Blocked") | F16: =COUNTIFS('Test Cases'!B2:B95,A16,'Test Cases'!L2:L95,"Not Run") | G16: =COUNTIFS('Test Cases'!B2:B95,A16,'Test Cases'!L2:L95,"N/A")
A17: AR · Matching | B17: =COUNTIF('Test Cases'!B2:B95,A17) | C17: =COUNTIFS('Test Cases'!B2:B95,A17,'Test Cases'!L2:L95,"Pass") | D17: =COUNTIFS('Test Cases'!B2:B95,A17,'Test Cases'!L2:L95,"Fail") | E17: =COUNTIFS('Test Cases'!B2:B95,A17,'Test Cases'!L2:L95,"Blocked") | F17: =COUNTIFS('Test Cases'!B2:B95,A17,'Test Cases'!L2:L95,"Not Run") | G17: =COUNTIFS('Test Cases'!B2:B95,A17,'Test Cases'!L2:L95,"N/A")
A18: AR · Deductions | B18: =COUNTIF('Test Cases'!B2:B95,A18) | C18: =COUNTIFS('Test Cases'!B2:B95,A18,'Test Cases'!L2:L95,"Pass") | D18: =COUNTIFS('Test Cases'!B2:B95,A18,'Test Cases'!L2:L95,"Fail") | E18: =COUNTIFS('Test Cases'!B2:B95,A18,'Test Cases'!L2:L95,"Blocked") | F18: =COUNTIFS('Test Cases'!B2:B95,A18,'Test Cases'!L2:L95,"Not Run") | G18: =COUNTIFS('Test Cases'!B2:B95,A18,'Test Cases'!L2:L95,"N/A")
A19: AR · Approval | B19: =COUNTIF('Test Cases'!B2:B95,A19) | C19: =COUNTIFS('Test Cases'!B2:B95,A19,'Test Cases'!L2:L95,"Pass") | D19: =COUNTIFS('Test Cases'!B2:B95,A19,'Test Cases'!L2:L95,"Fail") | E19: =COUNTIFS('Test Cases'!B2:B95,A19,'Test Cases'!L2:L95,"Blocked") | F19: =COUNTIFS('Test Cases'!B2:B95,A19,'Test Cases'!L2:L95,"Not Run") | G19: =COUNTIFS('Test Cases'!B2:B95,A19,'Test Cases'!L2:L95,"N/A")
A20: AR · SAP clearing | B20: =COUNTIF('Test Cases'!B2:B95,A20) | C20: =COUNTIFS('Test Cases'!B2:B95,A20,'Test Cases'!L2:L95,"Pass") | D20: =COUNTIFS('Test Cases'!B2:B95,A20,'Test Cases'!L2:L95,"Fail") | E20: =COUNTIFS('Test Cases'!B2:B95,A20,'Test Cases'!L2:L95,"Blocked") | F20: =COUNTIFS('Test Cases'!B2:B95,A20,'Test Cases'!L2:L95,"Not Run") | G20: =COUNTIFS('Test Cases'!B2:B95,A20,'Test Cases'!L2:L95,"N/A")
A21: AR · Playbook | B21: =COUNTIF('Test Cases'!B2:B95,A21) | C21: =COUNTIFS('Test Cases'!B2:B95,A21,'Test Cases'!L2:L95,"Pass") | D21: =COUNTIFS('Test Cases'!B2:B95,A21,'Test Cases'!L2:L95,"Fail") | E21: =COUNTIFS('Test Cases'!B2:B95,A21,'Test Cases'!L2:L95,"Blocked") | F21: =COUNTIFS('Test Cases'!B2:B95,A21,'Test Cases'!L2:L95,"Not Run") | G21: =COUNTIFS('Test Cases'!B2:B95,A21,'Test Cases'!L2:L95,"N/A")
A22: AR · Closure | B22: =COUNTIF('Test Cases'!B2:B95,A22) | C22: =COUNTIFS('Test Cases'!B2:B95,A22,'Test Cases'!L2:L95,"Pass") | D22: =COUNTIFS('Test Cases'!B2:B95,A22,'Test Cases'!L2:L95,"Fail") | E22: =COUNTIFS('Test Cases'!B2:B95,A22,'Test Cases'!L2:L95,"Blocked") | F22: =COUNTIFS('Test Cases'!B2:B95,A22,'Test Cases'!L2:L95,"Not Run") | G22: =COUNTIFS('Test Cases'!B2:B95,A22,'Test Cases'!L2:L95,"N/A")
A23: AI governance | B23: =COUNTIF('Test Cases'!B2:B95,A23) | C23: =COUNTIFS('Test Cases'!B2:B95,A23,'Test Cases'!L2:L95,"Pass") | D23: =COUNTIFS('Test Cases'!B2:B95,A23,'Test Cases'!L2:L95,"Fail") | E23: =COUNTIFS('Test Cases'!B2:B95,A23,'Test Cases'!L2:L95,"Blocked") | F23: =COUNTIFS('Test Cases'!B2:B95,A23,'Test Cases'!L2:L95,"Not Run") | G23: =COUNTIFS('Test Cases'!B2:B95,A23,'Test Cases'!L2:L95,"N/A")
A24: Security | B24: =COUNTIF('Test Cases'!B2:B95,A24) | C24: =COUNTIFS('Test Cases'!B2:B95,A24,'Test Cases'!L2:L95,"Pass") | D24: =COUNTIFS('Test Cases'!B2:B95,A24,'Test Cases'!L2:L95,"Fail") | E24: =COUNTIFS('Test Cases'!B2:B95,A24,'Test Cases'!L2:L95,"Blocked") | F24: =COUNTIFS('Test Cases'!B2:B95,A24,'Test Cases'!L2:L95,"Not Run") | G24: =COUNTIFS('Test Cases'!B2:B95,A24,'Test Cases'!L2:L95,"N/A")
A25: Workspace | B25: =COUNTIF('Test Cases'!B2:B95,A25) | C25: =COUNTIFS('Test Cases'!B2:B95,A25,'Test Cases'!L2:L95,"Pass") | D25: =COUNTIFS('Test Cases'!B2:B95,A25,'Test Cases'!L2:L95,"Fail") | E25: =COUNTIFS('Test Cases'!B2:B95,A25,'Test Cases'!L2:L95,"Blocked") | F25: =COUNTIFS('Test Cases'!B2:B95,A25,'Test Cases'!L2:L95,"Not Run") | G25: =COUNTIFS('Test Cases'!B2:B95,A25,'Test Cases'!L2:L95,"N/A")
A26: Operations | B26: =COUNTIF('Test Cases'!B2:B95,A26) | C26: =COUNTIFS('Test Cases'!B2:B95,A26,'Test Cases'!L2:L95,"Pass") | D26: =COUNTIFS('Test Cases'!B2:B95,A26,'Test Cases'!L2:L95,"Fail") | E26: =COUNTIFS('Test Cases'!B2:B95,A26,'Test Cases'!L2:L95,"Blocked") | F26: =COUNTIFS('Test Cases'!B2:B95,A26,'Test Cases'!L2:L95,"Not Run") | G26: =COUNTIFS('Test Cases'!B2:B95,A26,'Test Cases'!L2:L95,"N/A")
A27: Security · Approver | B27: =COUNTIF('Test Cases'!B2:B95,A27) | C27: =COUNTIFS('Test Cases'!B2:B95,A27,'Test Cases'!L2:L95,"Pass") | D27: =COUNTIFS('Test Cases'!B2:B95,A27,'Test Cases'!L2:L95,"Fail") | E27: =COUNTIFS('Test Cases'!B2:B95,A27,'Test Cases'!L2:L95,"Blocked") | F27: =COUNTIFS('Test Cases'!B2:B95,A27,'Test Cases'!L2:L95,"Not Run") | G27: =COUNTIFS('Test Cases'!B2:B95,A27,'Test Cases'!L2:L95,"N/A")
A28: Approvals | B28: =COUNTIF('Test Cases'!B2:B95,A28) | C28: =COUNTIFS('Test Cases'!B2:B95,A28,'Test Cases'!L2:L95,"Pass") | D28: =COUNTIFS('Test Cases'!B2:B95,A28,'Test Cases'!L2:L95,"Fail") | E28: =COUNTIFS('Test Cases'!B2:B95,A28,'Test Cases'!L2:L95,"Blocked") | F28: =COUNTIFS('Test Cases'!B2:B95,A28,'Test Cases'!L2:L95,"Not Run") | G28: =COUNTIFS('Test Cases'!B2:B95,A28,'Test Cases'!L2:L95,"N/A")
A29: AP · Re-run | B29: =COUNTIF('Test Cases'!B2:B95,A29) | C29: =COUNTIFS('Test Cases'!B2:B95,A29,'Test Cases'!L2:L95,"Pass") | D29: =COUNTIFS('Test Cases'!B2:B95,A29,'Test Cases'!L2:L95,"Fail") | E29: =COUNTIFS('Test Cases'!B2:B95,A29,'Test Cases'!L2:L95,"Blocked") | F29: =COUNTIFS('Test Cases'!B2:B95,A29,'Test Cases'!L2:L95,"Not Run") | G29: =COUNTIFS('Test Cases'!B2:B95,A29,'Test Cases'!L2:L95,"N/A")
A30: UI · Playbook | B30: =COUNTIF('Test Cases'!B2:B95,A30) | C30: =COUNTIFS('Test Cases'!B2:B95,A30,'Test Cases'!L2:L95,"Pass") | D30: =COUNTIFS('Test Cases'!B2:B95,A30,'Test Cases'!L2:L95,"Fail") | E30: =COUNTIFS('Test Cases'!B2:B95,A30,'Test Cases'!L2:L95,"Blocked") | F30: =COUNTIFS('Test Cases'!B2:B95,A30,'Test Cases'!L2:L95,"Not Run") | G30: =COUNTIFS('Test Cases'!B2:B95,A30,'Test Cases'!L2:L95,"N/A")
A31: AR · Correlation | B31: =COUNTIF('Test Cases'!B2:B95,A31) | C31: =COUNTIFS('Test Cases'!B2:B95,A31,'Test Cases'!L2:L95,"Pass") | D31: =COUNTIFS('Test Cases'!B2:B95,A31,'Test Cases'!L2:L95,"Fail") | E31: =COUNTIFS('Test Cases'!B2:B95,A31,'Test Cases'!L2:L95,"Blocked") | F31: =COUNTIFS('Test Cases'!B2:B95,A31,'Test Cases'!L2:L95,"Not Run") | G31: =COUNTIFS('Test Cases'!B2:B95,A31,'Test Cases'!L2:L95,"N/A")
A32: AR · Payment | B32: =COUNTIF('Test Cases'!B2:B95,A32) | C32: =COUNTIFS('Test Cases'!B2:B95,A32,'Test Cases'!L2:L95,"Pass") | D32: =COUNTIFS('Test Cases'!B2:B95,A32,'Test Cases'!L2:L95,"Fail") | E32: =COUNTIFS('Test Cases'!B2:B95,A32,'Test Cases'!L2:L95,"Blocked") | F32: =COUNTIFS('Test Cases'!B2:B95,A32,'Test Cases'!L2:L95,"Not Run") | G32: =COUNTIFS('Test Cases'!B2:B95,A32,'Test Cases'!L2:L95,"N/A")
A33: Client samples | B33: =COUNTIF('Test Cases'!B2:B95,A33) | C33: =COUNTIFS('Test Cases'!B2:B95,A33,'Test Cases'!L2:L95,"Pass") | D33: =COUNTIFS('Test Cases'!B2:B95,A33,'Test Cases'!L2:L95,"Fail") | E33: =COUNTIFS('Test Cases'!B2:B95,A33,'Test Cases'!L2:L95,"Blocked") | F33: =COUNTIFS('Test Cases'!B2:B95,A33,'Test Cases'!L2:L95,"Not Run") | G33: =COUNTIFS('Test Cases'!B2:B95,A33,'Test Cases'!L2:L95,"N/A")
A34: Total | B34: =SUM(B2:B33) | C34: =SUM(C2:C33) | D34: =SUM(D2:D33) | E34: =SUM(E2:E33) | F34: =SUM(F2:F33) | G34: =SUM(G2:G33)
A35: E2E AP (steps) | B35: =COUNTA('E2E AP'!A2:A11) | C35: =COUNTIF('E2E AP'!F2:F11,"Pass") | D35: =COUNTIF('E2E AP'!F2:F11,"Fail") | E35: =COUNTIF('E2E AP'!F2:F11,"Blocked") | F35: =COUNTIF('E2E AP'!F2:F11,"Not Run") | G35: =COUNTIF('E2E AP'!F2:F11,"N/A")
A36: E2E AR (steps) | B36: =COUNTA('E2E AR'!A2:A11) | C36: =COUNTIF('E2E AR'!F2:F11,"Pass") | D36: =COUNTIF('E2E AR'!F2:F11,"Fail") | E36: =COUNTIF('E2E AR'!F2:F11,"Blocked") | F36: =COUNTIF('E2E AR'!F2:F11,"Not Run") | G36: =COUNTIF('E2E AR'!F2:F11,"N/A")

Sheet Test Cases
A1: Test ID | B1: Area | C1: Scenario | D1: Priority | E1: Type | F1: Persona | G1: Preconditions / data | H1: Steps | I1: Expected result | J1: Evidence to capture | K1: Actual result | L1: Status | M1: Tester | N1: Date | O1: Defect ID | P1: Comments
A2: AP-INT-01 | B2: AP · Intake | C2: Upload an AP invoice and start processing | D2: High | E2: Positive | F2: AP Processor (bcfa.ap.processor) | G2: Demo pack prepared (Test Data R2). File test/fixtures/AP_INV_<suffix>_DEMO_NATIVE.pdf. | H2: 1. BCFA Workspace > Document Intake > New. 2. Document Type = AP Invoice. Attach the PDF. Save. 3. Click Process Document. | I2: Info message: "Native extraction is running (ServiceNow Document Intelligence)…". Intake Processing Status = Extracting; Extraction Provider = Native: ServiceNow Document Intelligence (Now LLM). | J2: Screenshot of the intake | L2: Not Run
A3: AP-INT-02 | B3: AP · Intake | C3: Asynchronous completion | D3: High | E3: Positive | F3: AP Processor (bcfa.ap.processor) | G3: AP-INT-01 done. | H3: 1. Wait about 1 minute (job BCFA - Native Extraction Poller runs every minute). 2. Refresh the intake. | I3: Processing Status = Completed; AP Invoice field links to INV-AP-<suffix>; Extraction Confidence = 1. | J3: Intake and invoice number | L3: Not Run
A4: AP-INT-03 | B4: AP · Intake | C4: Duplicate upload of the same file | D4: Medium | E4: Negative | F4: AP Processor (bcfa.ap.processor) | G4: AP-INT-02 done. | H4: 1. Create a new intake, attach the SAME PDF, Process Document. | I4: Processing Status = Completed with message "Duplicate of FDI-… — reusing its result, no new transaction created". No second invoice. | J4: Intake message | L4: Not Run
A5: AP-INT-04 | B5: AP · Intake | C5: Document type missing | D5: Medium | E5: Negative | F5: AP Processor (bcfa.ap.processor) | G5: — | H5: 1. New intake without Document Type (or Unknown), attach any PDF, Save, Process Document. | I5: Processing Status = Review Required: "Set the document type … then process the document again." Nothing extracted. | J5: Intake message | L5: Not Run
A6: AP-OCR-01 | B6: AP · Extraction | C6: Header and line fields read natively | D6: High | E6: Positive | F6: AP Processor (bcfa.ap.processor) | G6: AP-INT-02 done. | H6: 1. Open INV-AP-<suffix>. Read the Review Summary and the Extraction related list. 2. Compare with the PDF. | I6: Vendor Rajasthan Carbon Feedstock Pvt Ltd, PO0001, INR, net 5,000, IGST 900, total 5,900, 1 line 100 MT × 50. Extraction source = ServiceNow Document Intelligence (Now LLM); banner NATIVE EXTRACTION. | J6: Review Summary screenshot | L6: Not Run
A7: AP-OCR-02 | B7: AP · Extraction | C7: Tax breakdown, country and language recorded as printed | D7: High | E7: Positive | F7: AP Processor (bcfa.ap.processor) | G7: AP-INT-02 done. | H7: 1. On INV-AP-<suffix> check Tax Type, Tax Rate Pct, IGST Amount, Document Country, Document Language. | I7: Tax Type IGST, rate 18, IGST 900, country India, language English. | J7: Field values | L7: Not Run
A8: AP-OCR-03 | B8: AP · Extraction | C8: Multi-country fixture read (vendor not in master data) | D8: Medium | E8: Positive | F8: AP Processor (bcfa.ap.processor) | G8: Fixture test/fixtures/AP_INV_103_VAT7_DE.pdf (German, MwSt. 7 %). | H8: 1. New intake, AP Invoice, attach the PDF, Process Document; wait 1 minute; refresh. 2. Open Extraction JSON on the intake. | I8: Extraction JSON shows Elbtal Fachverlag GmbH, R-2026-3391, EUR, net 2058.80, tax 144.12, total 2202.92, rate 7, 2 lines. Intake Completed and an AP invoice is created with Vendor (Printed) Elbtal Fachverlag GmbH; the invoice goes to EXCEPTION Vendor Invalid (the vendor is not in the demo master data) — expected. | J8: Extraction JSON, invoice and exception | L8: Not Run
A9: AP-OCR-04 | B9: AP · Extraction | C9: Low confidence goes to a person | D9: High | E9: Negative | F9: AP Processor (bcfa.ap.processor) | G9: Fixture AP_INV_006_LOW_CONFIDENCE.pdf (vendor unreadable). | H9: 1. New intake, AP Invoice, attach, Process Document; wait; refresh. | I9: Review Required with message "Extraction confidence … is below the 0.85 review threshold" and the warnings (e.g. Required field not read: vendor_name). No invoice created. | J9: Intake message | L9: Not Run
A10: AP-OCR-05 | B10: AP · Extraction | C10: No fallback to simulated values | D10: High | E10: Negative | F10: Admin | G10: Property document.extraction.provider = native. | H10: 1. Review the CP-EXT ATF result (Test Data R4) or upload a non-invoice PDF as AP Invoice. | I10: A document that cannot be read goes to manual review; nothing is filled from fixture values; no SIMULATED label appears. | J10: ATF result / intake | L10: Not Run
A11: AP-VAL-01 | B11: AP · Validation | C11: Duplicate invoice detected | D11: High | E11: Negative | F11: AP Processor (bcfa.ap.processor) | G11: Demo data reset done (Test Data sheet, step R1). | H11: 1. Open the AP exception of INV-AP-001 with reason Duplicate (scenario AP-002). | I11: Reason Duplicate, severity High, rule result names the earlier invoice; journey stage 3 blocked. | J11: Exception | L11: Not Run
A12: AP-VAL-02 | B12: AP · Validation | C12: PO mismatch | D12: Medium | E12: Negative | F12: AP Processor (bcfa.ap.processor) | G12: Demo data reset done (Test Data sheet, step R1). | H12: 1. Open INV-AP-003 and its exception. | I12: Exception PO mismatch; stage 3 blocked; WHY explains the PO check. | J12: Exception | L12: Not Run
A13: AP-TAX-01 | B13: AP · Tax | C13: Valid GST (IGST) passes | D13: High | E13: Positive | F13: AP Processor (bcfa.ap.processor) | G13: AP-INT-02 done. | H13: 1. On INV-AP-<suffix> read Tax Regime, Expected Tax Amount, Tax Validation, Tax Validation Detail, Tax Rule Source. | I13: Regime GST, expected 900, result Pass; detail lists "PASS: tax 900 vs expected 900 …" and "PASS: IGST 900 (inter-state) agrees with the total tax"; rule source = decision table BCFA AP Tax Expectation (India: GST 18 %) - POC REFERENCE DATA. | J13: Tax fields | L13: Not Run
... A95: P41-CS-05 | B95: Client samples | C95: Chinese / Korean / Thai invoices (known platform limitation) | D95: High | E95: Negative | F95: AP Processor (bcfa.ap.processor) | G95: Client pack, CS-18, CS-19, CS-26. | H95: 1. Upload as AP Invoice; Process Document. | I95: Fields not read are left empty (no value invented); confidence low; review. See MULTILINGUAL_DOCUMENT_INTELLIGENCE_READINESS.md. | J95: Intakes | L95: Not Run

Sheet E2E AP
A1: Step | B1: Persona | C1: Action | D1: Expected result | E1: Actual result | F1: Status | G1: Tester | H1: Date | I1: Notes
A2: Prepare | B2: Admin | C2: Run scripts/deploy/phase40_demo_prep_<suffix>_bg.js (Scripts - Background, scope x_695068_bcfa). | D2: Log line BCFA_DEMO40 prep <suffix>: open items and bank line created. | F2: Not Run
A3: 1 Intake | B3: AP Processor (bcfa.ap.processor) | C3: Document Intake > New; Document Type AP Invoice; attach AP_INV_<suffix>_DEMO_NATIVE.pdf; Save; Process Document. | D3: Extracting; message about native extraction. | F3: Not Run
A4: 2 Extraction | B4: AP Processor (bcfa.ap.processor) | C4: Wait ~1 minute; refresh the intake; open the invoice. | D4: Intake Completed; INV-AP-<suffix> created; NATIVE EXTRACTION banner; confidence 1. | F4: Not Run
A5: 3 Validation | B5: AP Processor (bcfa.ap.processor) | C5: Read the Review Summary (vendor, PO, duplicate check). | D5: Vendor Rajasthan Carbon Feedstock Pvt Ltd, PO0001; no exception. | F5: Not Run
A6: 4 Tax | B6: AP Processor (bcfa.ap.processor) | C6: Read Tax Validation fields. | D6: GST regime, expected 900, Pass, rule source decision table. | F6: Not Run
A7: 5 Match | B7: AP Processor (bcfa.ap.processor) | C7: AP Match related list. | D7: Matched within tolerance; tolerance detail per check. | F7: Not Run
A8: 6 Playbook | B8: AP Processor (bcfa.ap.processor) | C8: Open Playbook. | D8: Stages 1–5 complete; stage 6 Approval in progress, owner Finance Approver. | F8: Not Run
A9: 7 Approval | B9: Finance Approver (bcfa.finance.approver) | C9: AP > Approvals > Approve. | D9: Approval decided with SoD checks. | F9: Not Run
A10: 8 SAP posting | B10: Finance Approver (bcfa.finance.approver) | C10: Refresh the invoice; Integration Transactions. | D10: postVendorInvoice success, MIRO… document, POSTED. | F10: Not Run
A11: 9 Closure | B11: Auditor | C11: Refresh; Audit Events; Playbook. | D11: CLOSED; all 8 stages complete; full audit chain. | F11: Not Run

Sheet E2E AR
A1: Step | B1: Persona | C1: Action | D1: Expected result | E1: Actual result | F1: Status | G1: Tester | H1: Date | I1: Notes
A2: Prepare | B2: Admin | C2: Same prep script as AP (creates ARINV-<suffix>-01/02 and bank line NRC-PAY-26-<suffix>). | D2: Open items and bank line exist. | F2: Not Run
A3: 1 Bank line | B3: AR Processor (bcfa.ar.processor) | C3: Payments > NRC-PAY-26-<suffix>. | D3: EXCEPTION, customer ambiguous, waiting for the advice (stage 3). | F3: Not Run
A4: 2 Advice intake | B4: AR Processor (bcfa.ar.processor) | C4: Document Intake > New; AR Payment Advice; attach AR_REMIT_<suffix>_DEMO_NATIVE.pdf; Save; Process Document. | D4: Extracting. | F4: Not Run
A5: 3 Extraction and correlation | B5: AR Processor (bcfa.ar.processor) | C5: Wait ~1 minute; refresh the intake and the payment. | D5: Intake Completed; remittance linked; customer Nilgiri Rubber Compounds Ltd. | F5: Not Run
A6: 4 Open items | B6: AR Processor (bcfa.ar.processor) | C6: Payment > Integration Transactions. | D6: getOpenItems success (MOCK SAP). | F6: Not Run
A7: 5 Match and allocation | B7: AR Processor (bcfa.ar.processor) | C7: Match Candidates, Allocations. | D7: Both references matched; allocated 80,000; residual −1,600. | F7: Not Run
A8: 6 Deduction | B8: AR Processor (bcfa.ar.processor) | C8: Short Pay exception: Deduction Type Withholding Tax, Decision Reason; Update; Approve Deduction. | D8: Deduction 1,600 withholding recorded (human_confirmed); payment PENDING_APPROVAL. | F8: Not Run
A9: 7 Approval | B9: Finance Approver (bcfa.finance.approver) | C9: Cash Application > Approvals > Approve. | D9: Approved with SoD checks. | F9: Not Run
A10: 8 SAP clearing | B10: Finance Approver (bcfa.finance.approver) | C10: Refresh payment; Integration Transactions; open items. | D10: clearCustomerPayment success FB05… (DIRECT); open items settled; CLOSED. | F10: Not Run
A11: 9 Closure | B11: Auditor | C11: Playbook; Audit Events. | D11: All 9 stages complete; full audit chain. | F11: Not Run

Sheet Test Data
A1: Ref | B1: Item | C1: Detail
A2: R1 | B2: Demo data reset (optional, on agreement) | C2: Admin: Scripts - Background, scope x_695068_bcfa, run scripts/deploy/phase28_reset_and_reseed_bg.js. Restores INV-AP-001..010, BANK-AR-001..010, BANK-POC2-001..003, INV-PLAY-01..04, BANK-PLAY-01..07.
A3: R2 | B3: Fresh demo pack for E2E tests | C3: python scripts/fixtures/gen_phase40_demo_journeys.py <suffix> (new suffix per run, e.g. T1), then run scripts/deploy/phase40_demo_prep_<suffix>_bg.js (scope x_695068_bcfa). Packs D1 (used for rehearsal on 2026-10-05) and D2 (reserved for the client demo) already exist.
A4: R3 | B4: Tax / tolerance / deduction scenarios | C4: Run scripts/deploy/phase40_e2e_bg.js (scope x_695068_bcfa). Creates invoices E2E-<run>-T1, T2, T4, T5, T6, Q1, Q2 and payments E2E-<run>-T, U, R; the log line BCFA_E2E40 run <run> lists the results.
A5: R4 | B5: Automated regression | C5: Run the ATF suite BCFA Regression (49 tests), one test at a time if the instance is busy; results in Automated Test Framework > Test Results.
A6: Users | B6: Personas | C6: bcfa.ap.processor, bcfa.ar.processor, bcfa.finance.approver, bcfa.finance.controller (impersonate from an admin account; no passwords needed).
A7: Fixtures | B7: Synthetic PDFs | C7: test/fixtures: AP_INV_001..006, AP_INV_101..105 (GST, IGST, German VAT, WHT, 2-page), AR_REMIT_001..005, 101..103, 201..204, *_D1/_D2_DEMO_NATIVE. All watermarked SYNTHETIC.
A8: Properties | B8: Settings used by tests | C8: x_695068_bcfa.document.extraction.provider (native), x_695068_bcfa.sap.adapter (mock_sap), x_695068_bcfa.ar.sap_processing_mode (direct / draft), x_695068_bcfa.mock_sap.draft_outcome, Integration Profile "Mock SAP - Default" failure mode. Restore after each negative test.
A9: Workspace | B9: URL | C9: https://pwcmanagementservicesdemo01.service-now.com/now/bcfa/home

Sheet Defects
A1: Defect ID | B1: Test ID | C1: Summary | D1: Steps to reproduce | E1: Expected | F1: Actual | G1: Severity | H1: Status | I1: Raised by | J1: Date | K1: Owner | L1: Resolution
A2: D6 | B2: AP-EXC-05 | C2: Finance approver cannot type the Decision Reason on an exception | D2: Impersonate bcfa.finance.approver; open an AP exception; try to edit Decision Reason | E2: Approver can enter the reason | F2: Field read-only (write ACL allows processor and admin only) | G2: Medium | H2: Open | I2: Build team | J2: 2026-10-05 | K2: Instance owner / security_admin | L2: Workaround: processor enters the reason, approver approves
